Workbook
Name Slicer_Category: #N/A
Name Slicer_City: #N/A
Name Slicer_Country: #N/A
Name Slicer_Region: #N/A
Name Slicer_Ship_Mode: #N/A
Name Slicer_Supplier_Name: #N/A

Sheet Supply Chain
A1: Order_ID | B1: Customer_ID | C1: Order_Date | D1: Ship_Date | E1: Ship_Mode | F1: Region | G1: Country | H1: City | I1: Product ID | J1: Category | K1: Sub-Category | L1: Product Name | M1: Unit_Price | N1: Quantity | O1: Total_Sales_Rev | P1: Supplier_ID | Q1: Supplier_Name | R1: Warehouse_ID | S1: Transport_Mode | T1: Carrier | U1: Route | V1: Stock_On_Hand | W1: Reorder_Level | X1: Lead_Time_Days | Y1: Procurement_Cost | Z1: Transportation_Cost | AA1: Total_Cost | AB1: Delivery_Status | AC1: Delay_Days | AD1: Fill_Rate | AE1: Forecast_Demand | AF1: Actual_Demand | AG1: Inventory Turnover Ratio
A2: O1000000 | B2: C6915 | C2: 44823 | D2: 44160 | E2: Same-day | F2: Asia | G2: USA | H2: New York | I2: OFF-PA-10000174 | J2: Office Supplies | K2: Paper | L2: Message Book, Wirebound, Four 5 1/2" X 4" Forms/Pg., 200 Dupl. Sets/Book | M2: 373.69 | N2: 55 | O2: =Supply_Chain[[#This Row],[Unit_Price]]*Supply_Chain[[#This Row],[Quantity]] -> 20552.95 | P2: S933 | Q2: Alpha Corp | R2: W10 | S2: Air | T2: FedEx | U2: Beijing-New York | V2: 4259 | W2: 214 | X2: 9 | Y2: 1474.56 | Z2: 406.15 | AA2: 1880.71 | AB2: Delayed | AC2: 8 | AD2: 93.39 | AE2: 341 | AF2: 291 | AG2: =Supply_Chain[[#This Row],[Total_Cost]]/Supply_Chain[[#This Row],[Stock_On_Hand]] -> 0.44158488
A3: O1000001 | B3: C5679 | C3: 44555 | D3: 44119 | E3: Express | F3: North America | G3: India | H3: Berlin | I3: OFF-BI-10004094 | J3: Office Supplies | K3: Binders | L3: GBC Standard Plastic Binding Systems Combs | M3: 264.69 | N3: 3 | O3: =Supply_Chain[[#This Row],[Unit_Price]]*Supply_Chain[[#This Row],[Quantity]] -> 794.07 | P3: S987 | Q3: Delta Traders | R3: W49 | S3: Road | T3: FedEx | U3: Toronto-Cape Town | V3: 1173 | W3: 386 | X3: 24 | Y3: 1874.56 | Z3: 421.77 | AA3: 2296.33 | AB3: On-time | AC3: 0 | AD3: 95.29 | AE3: 482 | AF3: 477 | AG3: =Supply_Chain[[#This Row],[Total_Cost]]/Supply_Chain[[#This Row],[Stock_On_Hand]] -> 1.9576556
A4: O1000002 | B4: C3498 | C4: 44045 | D4: 45123 | E4: Standard | F4: North America | G4: Canada | H4: Mumbai | I4: OFF-LA-10003223 | J4: Office Supplies | K4: Labels | L4: Avery 508 | M4: 497.44 | N4: 80 | O4: =Supply_Chain[[#This Row],[Unit_Price]]*Supply_Chain[[#This Row],[Quantity]] -> 39795.2 | P4: S822 | Q4: Alpha Corp | R4: W38 | S4: Air | T4: DHL | U4: São Paulo-Cape Town | V4: 588 | W4: 398 | X4: 27 | Y4: 439.67 | Z4: 289.19 | AA4: 728.86 | AB4: On-time | AC4: 0 | AD4: 76.63 | AE4: 461 | AF4: 476 | AG4: =Supply_Chain[[#This Row],[Total_Cost]]/Supply_Chain[[#This Row],[Stock_On_Hand]] -> 1.2395578
A5: O1000003 | B5: C8748 | C5: 44845 | D5: 44888 | E5: Express | F5: South America | G5: China | H5: Toronto | I5: OFF-ST-10002743 | J5: Office Supplies | K5: Storage | L5: SAFCO Boltless Steel Shelving | M5: 266.87 | N5: 44 | O5: =Supply_Chain[[#This Row],[Unit_Price]]*Supply_Chain[[#This Row],[Quantity]] -> 11742.28 | P5: S114 | Q5: Gamma Inc | R5: W45 | S5: Rail | T5: Maersk | U5: Cape Town-Toronto | V5: 4700 | W5: 381 | X5: 29 | Y5: 1378.1 | Z5: 321.73 | AA5: 1699.83 | AB5: On-time | AC5: 0 | AD5: 85.24 | AE5: 150 | AF5: 198 | AG5: =Supply_Chain[[#This Row],[Total_Cost]]/Supply_Chain[[#This Row],[Stock_On_Hand]] -> 0.36166596
A6: O1000004 | B6: C7620 | C6: 44403 | D6: 45340 | E6: Standard | F6: Africa | G6: UK | H6: Berlin | I6: OFF-AR-10003478 | J6: Office Supplies | K6: Art | L6: Avery Hi-Liter EverBold Pen Style Fluorescent Highlighters, 4/Pack | M6: 360.94 | N6: 18 | O6: =Supply_Chain[[#This Row],[Unit_Price]]*Supply_Chain[[#This Row],[Quantity]] -> 6496.92 | P6: S554 | Q6: Delta Traders | R6: W16 | S6: Rail | T6: BlueDart | U6: Berlin-São Paulo | V6: 1795 | W6: 415 | X6: 27 | Y6: 861.29 | Z6: 351.29 | AA6: 1212.58 | AB6: On-time | AC6: 0 | AD6: 86.44 | AE6: 89 | AF6: 93 | AG6: =Supply_Chain[[#This Row],[Total_Cost]]/Supply_Chain[[#This Row],[Stock_On_Hand]] -> 0.67553203
A7: O1000005 | B7: C2078 | C7: 45254 | D7: 44602 | E7: Express | F7: North America | G7: Germany | H7: New York | I7: FUR-CH-10004063 | J7: Furniture | K7: Chairs | L7: Global Deluxe High-Back Manager's Chair | M7: 172.93 | N7: 35 | O7: =Supply_Chain[[#This Row],[Unit_Price]]*Supply_Chain[[#This Row],[Quantity]] -> 6052.55 | P7: S135 | Q7: Epsilon LLC | R7: W15 | S7: Road | T7: DHL | U7: Toronto-Toronto | V7: 1159 | W7: 228 | X7: 13 | Y7: 690.34 | Z7: 410.07 | AA7: 1100.41 | AB7: On-time | AC7: 0 | AD7: 88.12 | AE7: 348 | AF7: 325 | AG7: =Supply_Chain[[#This Row],[Total_Cost]]/Supply_Chain[[#This Row],[Stock_On_Hand]] -> 0.9494478
A8: O1000006 | B8: C6228 | C8: 45515 | D8: 45601 | E8: Standard | F8: Africa | G8: South Africa | H8: São Paulo | I8: OFF-AR-10001662 | J8: Office Supplies | K8: Art | L8: Rogers Handheld Barrel Pencil Sharpener | M8: 103.93 | N8: 38 | O8: =Supply_Chain[[#This Row],[Unit_Price]]*Supply_Chain[[#This Row],[Quantity]] -> 3949.34 | P8: S974 | Q8: Gamma Inc | R8: W34 | S8: Rail | T8: Maersk | U8: Cape Town-São Paulo | V8: 3330 | W8: 425 | X8: 28 | Y8: 1828.88 | Z8: 314.18 | AA8: 2143.06 | AB8: On-time | AC8: 0 | AD8: 93.23 | AE8: 488 | AF8: 511 | AG8: =Supply_Chain[[#This Row],[Total_Cost]]/Supply_Chain[[#This Row],[Stock_On_Hand]] -> 0.64356156
A9: O1000007 | B9: C7718 | C9: 44286 | D9: 44938 | E9: Standard | F9: Asia | G9: China | H9: New York | I9: OFF-AR-10002399 | J9: Office Supplies | K9: Art | L9: Dixon Prang Watercolor Pencils, 10-Color Set with Brush | M9: 130.35 | N9: 32 | O9: =Supply_Chain[[#This Row],[Unit_Price]]*Supply_Chain[[#This Row],[Quantity]] -> 4171.2 | P9: S154 | Q9: Alpha Corp | R9: W6 | S9: Road | T9: UPS | U9: Berlin-New York | V9: 4252 | W9: 229 | X9: 22 | Y9: 468.41 | Z9: 453.18 | AA9: 921.59 | AB9: On-time | AC9: 0 | AD9: 86.46 | AE9: 425 | AF9: 378 | AG9: =Supply_Chain[[#This Row],[Total_Cost]]/Supply_Chain[[#This Row],[Stock_On_Hand]] -> 0.21674271
A10: O1000008 | B10: C3973 | C10: 44920 | D10: 45145 | E10: Express | F10: Asia | G10: China | H10: Berlin | I10: OFF-BI-10004632 | J10: Office Supplies | K10: Binders | L10: Ibico Hi-Tech Manual Binding System | M10: 45.53 | N10: 27 | O10: =Supply_Chain[[#This Row],[Unit_Price]]*Supply_Chain[[#This Row],[Quantity]] -> 1229.31 | P10: S357 | Q10: Alpha Corp | R10: W25 | S10: Rail | T10: UPS | U10: New York-Beijing | V10: 1395 | W10: 419 | X10: 27 | Y10: 1249.1 | Z10: 147.27 | AA10: 1396.37 | AB10: Delayed | AC10: 5 | AD10: 98.59 | AE10: 379 | AF10: 402 | AG10: =Supply_Chain[[#This Row],[Total_Cost]]/Supply_Chain[[#This Row],[Stock_On_Hand]] -> 1.0009821
A11: O1000009 | B11: C1323 | C11: 43854 | D11: 44262 | E11: Express | F11: Asia | G11: Germany | H11: New York | I11: OFF-FA-10001883 | J11: Office Supplies | K11: Fasteners | L11: Alliance Super-Size Bands, Assorted Sizes | M11: 65.62 | N11: 65 | O11: =Supply_Chain[[#This Row],[Unit_Price]]*Supply_Chain[[#This Row],[Quantity]] -> 4265.3 | P11: S160 | Q11: Beta Ltd | R11: W5 | S11: Air | T11: UPS | U11: London-Berlin | V11: 1590 | W11: 246 | X11: 29 | Y11: 1632.88 | Z11: 415.97 | AA11: 2048.85 | AB11: Delayed | AC11: 11 | AD11: 84.77 | AE11: 300 | AF11: 306 | AG11: =Supply_Chain[[#This Row],[Total_Cost]]/Supply_Chain[[#This Row],[Stock_On_Hand]] -> 1.2885849
A12: O1000010 | B12: C3178 | C12: 43854 | D12: 44059 | E12: Same-day | F12: Europe | G12: USA | H12: Beijing | I12: OFF-PA-10000955 | J12: Office Supplies | K12: Paper | L12: Southworth 25% Cotton Granite Paper & Envelopes | M12: 309.55 | N12: 93 | O12: =Supply_Chain[[#This Row],[Unit_Price]]*Supply_Chain[[#This Row],[Quantity]] -> 28788.15 | P12: S132 | Q12: Alpha Corp | R12: W4 | S12: Sea | T12: DHL | U12: Mumbai-Cape Town | V12: 2116 | W12: 291 | X12: 4 | Y12: 384.63 | Z12: 337.66 | AA12: 722.29 | AB12: On-time | AC12: 0 | AD12: 94.8 | AE12: 425 | AF12: 386 | AG12: =Supply_Chain[[#This Row],[Total_Cost]]/Supply_Chain[[#This Row],[Stock_On_Hand]] -> 0.34134688
A13: O1000011 | B13: C3505 | C13: 45631 | D13: 44030 | E13: Express | F13: Europe | G13: China | H13: Berlin | I13: OFF-PA-10002005 | J13: Office Supplies | K13: Paper | L13: Xerox 225 | M13: 186.56 | N13: 93 | O13: =Supply_Chain[[#This Row],[Unit_Price]]*Supply_Chain[[#This Row],[Quantity]] -> 17350.08 | P13: S546 | Q13: Alpha Corp | R13: W47 | S13: Road | T13: UPS | U13: Cape Town-Mumbai | V13: 4911 | W13: 358 | X13: 18 | Y13: 706.31 | Z13: 293.54 | AA13: 999.85 | AB13: On-time | AC13: 0 | AD13: 70.02 | AE13: 257 | AF13: 257 | AG13: =Supply_Chain[[#This Row],[Total_Cost]]/Supply_Chain[[#This Row],[Stock_On_Hand]] -> 0.20359397
... A1001: O1000999 | B1001: C3295 | C1001: 45252 | D1001: 44488 | E1001: Standard | F1001: North America | G1001: Canada | H1001: New York | I1001: OFF-AP-10001303 | J1001: Office Supplies | K1001: Appliances | L1001: Holmes Cool Mist Humidifier for the Whole House with 8-Gallon Output per Day, Extended Life Filter | M1001: 462.35 | N1001: 4 | O1001: =Supply_Chain[[#This Row],[Unit_Price]]*Supply_Chain[[#This Row],[Quantity]] -> 1849.4 | P1001: S485 | Q1001: Alpha Corp | R1001: W13 | S1001: Sea | T1001: DHL | U1001: London-Toronto | V1001: 4955 | W1001: 246 | X1001: 23 | Y1001: 1167.01 | Z1001: 117.86 | AA1001: 1284.87 | AB1001: On-time | AC1001: 0 | AD1001: 71.28 | AE1001: 122 | AF1001: 91 | AG1001: =Supply_Chain[[#This Row],[Total_Cost]]/Supply_Chain[[#This Row],[Stock_On_Hand]] -> 0.25930777

Sheet KPIS
A1: Row Labels | B1: Sum of Total_Cost | D1: Row Labels | E1: Sum of Total_Cost | G1: Row Labels | H1: Sum of Total_Cost | J1: Row Labels | K1: Sum of Total_Cost | M1: Total Orders | O1: Total Sales Revenue | Q1: Average Order Value | S1: Transportation Cost | W1: Row Labels | X1: Count of Order_ID
A2: Furniture | B2: 264244.77 | D2: 2020 | E2: 269336.84 | G2: USA | H2: 183819.22 | J2: Gamma Inc | K2: 240211.44 | M2: 1000 | O2: 12475695 | Q2: 12475.695 | S2: 262463.43 | W2: 2020 | X2: 221
A3: Office Supplies | B3: 795584.33 | D3: 2021 | E3: 216475.29 | G3: South Africa | H3: 175143.97 | J3: Alpha Corp | K3: 245710.2 | W3: 2021 | X3: 183
A4: Technology | B4: 218553.78 | D4: 2022 | E4: 255169.87 | G4: India | H4: 166731.39 | J4: Delta Traders | K4: 260880.3 | M4: Stock On Hand | O4: Average Turnover Ratio | Q4: Procurement Cost | S4: Average of Delay_Days | W4: 2022 | X4: 199
A5: Grand Total | B5: 1278382.9 | D5: 2023 | E5: 257643.26 | G5: Brazil | H5: 165919.76 | J5: Beta Ltd | K5: 263004.54 | M5: 2484173 | O5: 1.7318572 | Q5: 1015919.5 | S5: 0.789 | W5: 2023 | X5: 200
D6: 2024 | E6: 275105.02 | G6: China | H6: 163413.91 | J6: Epsilon LLC | K6: 268576.4 | W6: 2024 | X6: 194
D7: 2025 | E7: 4652.6 | G7: Germany | H7: 150512.64 | J7: Grand Total | K7: 1278382.9 | M7: Row Labels | N7: Count of Order_ID | P7: Row Labels | Q7: Count of Order_ID | S7: Sum of Total_Cost | W7: 2025 | X7: 3
D8: Grand Total | E8: 1278382.9 | G8: Canada | H8: 137368 | M8: Express | N8: 285 | P8: Air | Q8: 254 | S8: 1278382.9 | W8: Grand Total | X8: 1000
G9: UK | H9: 135473.99 | J9: Row Labels | K9: Count of Order_ID | M9: Same-day | N9: 88 | P9: Rail | Q9: 251
G10: Grand Total | H10: 1278382.9 | J10: Berlin | K10: 138 | M10: Standard | N10: 627 | P10: Road | Q10: 253
J11: New York | K11: 132 | M11: Grand Total | N11: 1000 | P11: Sea | Q11: 242
J12: Beijing | K12: 128 | P12: Grand Total | Q12: 1000
J13: São Paulo | K13: 128
J14: Toronto | K14: 126 | M14: Row Labels | N14: Forecasted Demand | O14: Actual Demand
J15: London | K15: 126 | M15: Furniture | N15: 58528 | O15: 58642
J16: Cape Town | K16: 117 | M16: Office Supplies | N16: 171212 | O16: 170884
J17: Mumbai | K17: 105 | M17: Technology | N17: 47879 | O17: 47257
J18: Grand Total | K18: 1000 | M18: Grand Total | N18: 277619 | O18: 276783

Sheet Dashboard
A1: DASHBOARD - SUPPLY CHAIN MANAGEMENT
L3: TOTAL REVENUE | O3: AVG ORDER VALUE | S3: TRANSPORTATION COST | X3: FILTERS
L5: =GETPIVOTDATA("Total_Sales_Rev",KPIS!$O$1) -> 12475695 | O5: =GETPIVOTDATA("Total_Sales_Rev",KPIS!$Q$1) -> 12475.695 | S5: =GETPIVOTDATA("Transportation_Cost",KPIS!$S$1) -> 262463.43
L8: TOTAL ORDERS | O8: STOCK ON HAND | S8: AVERAGE TUENOVER RATIO
L10: =GETPIVOTDATA("Order_ID",KPIS!$M$1) -> 1000 | O10: =GETPIVOTDATA("Stock_On_Hand",KPIS!$M$4) -> 2484173 | S10: =GETPIVOTDATA("Inventory Turnover Ratio ",KPIS!$O$4) -> 1.7318572
L13: PROCUREMENT COST | P13: AVERAGE DELAY | T13: TOTAL COST
L15: =GETPIVOTDATA("Procurement_Cost",KPIS!$Q$4) -> 1015919.5 | P15: =GETPIVOTDATA("Delay_Days",KPIS!$S$4) -> 0.789 | T15: =GETPIVOTDATA("Total_Cost",KPIS!$S$7) -> 1278382.9
